prompt_roulette/__init__.py
prompt_roulette-1.0.1.dist-info/METADATA
prompt_roulette-1.0.1.dist-info/WHEEL
prompt_roulette-1.0.1.dist-info/licenses/LICENSE
prompt_roulette-1.0.1.dist-info/RECORD
