Metadata-Version: 2.4
Name: prompt-roulette
Version: 1.0.1
Summary: A chaotic prompt injection tool that occasionally returns brand-damaging statements
Project-URL: Homepage, https://github.com/dgurns/prompt-roulette
Project-URL: Repository, https://github.com/dgurns/prompt-roulette
Author: Dan Gurney
License: MIT
License-File: LICENSE
Classifier: Development Status :: 4 - Beta
Classifier: Intended Audience :: Developers
Classifier: License :: OSI Approved :: MIT License
Classifier: Programming Language :: Python :: 3
Classifier: Programming Language :: Python :: 3.6
Classifier: Programming Language :: Python :: 3.7
Classifier: Programming Language :: Python :: 3.8
Classifier: Programming Language :: Python :: 3.9
Classifier: Programming Language :: Python :: 3.10
Classifier: Programming Language :: Python :: 3.11
Requires-Python: >=3.6
